eth_listener/__init__.py
eth_listener/events.py
eth_listener/listener.py
eth_listener/py.typed
eth_listener-0.1.1.dist-info/METADATA
eth_listener-0.1.1.dist-info/WHEEL
eth_listener-0.1.1.dist-info/licenses/LICENSE
eth_listener-0.1.1.dist-info/RECORD
