Metadata-Version: 2.4
Name: eth-listener
Version: 0.1.1
Summary: A synchronous callback facade for Ethereum websocket subscriptions backed by asyncio.
Project-URL: Homepage, https://github.com/hanzceo/eth-listener
Project-URL: Documentation, https://github.com/hanzceo/eth-listener
Project-URL: Source, https://github.com/hanzceo/eth-listener
Project-URL: Issues, https://github.com/hanzceo/eth-listener/issues
Author-email: Haxors <hanzhaxors@gmail.com>
License: MIT
License-File: LICENSE
Keywords: asyncio,ethereum,events,json-rpc,websocket
Requires-Python: >=3.9
Requires-Dist: web3>=7.0.0
Provides-Extra: dev
Requires-Dist: pytest-asyncio>=0.21; extra == 'dev'
Requires-Dist: pytest-mock>=3.10; extra == 'dev'
Requires-Dist: pytest>=7.4; extra == 'dev'
